singlecell_NMF/NMF.py
singlecell_NMF/__init__.py
singlecell_NMF/coupledNMF.py
singlecell_NMF-0.0.4.dist-info/METADATA
singlecell_NMF-0.0.4.dist-info/WHEEL
singlecell_NMF-0.0.4.dist-info/top_level.txt
singlecell_NMF-0.0.4.dist-info/RECORD
