Metadata-Version: 2.1
Name: singlecell-NMF
Version: 0.0.4
Summary: singlecell-NMF: a python package provides NMF and CoupledNMF for clustering large-scale single-cell expression data .
Home-page: https://github.com/wangzichenbioinformatics/singlecell-NMF
Author: Wangchen
Author-email: wch_bioinformatics@163.com
License: UNKNOWN
Platform: UNKNOWN
Classifier: Programming Language :: Python :: 3
Classifier: License :: OSI Approved :: MIT License
Classifier: Operating System :: OS Independent
Requires-Python: >=3.9
